{
  "brand": "The Mars Lounge Bar",
  "language": "pl",
  "menu": {
    "kraftowe_drinki": [
      {
        "id": 1,
        "name": "Tokyo Night",
        "price": 39,
        "volume_ml": 350,
        "description": "Słodko‑kwaśny koktajl przygotowany z puree z marakui, Sprite, syropem wiśniowym i japońskim ginem."
      },
      {
        "id": 2,
        "name": "Soprano",
        "price": 34,
        "volume_ml": 120,
        "description": "Słodki koktajl przygotowany z espresso, Baileys i likierem migdałowym."
      },
      {
        "id": 3,
        "name": "Supernova",
        "price": 38,
        "volume_ml": 150,
        "description": "Kwaśny koktajl przygotowany z puree z marakui, wódki waniliowej, soku z limonki z dodatkiem prosecco."
      },
      {
        "id": 4,
        "name": "Onyx Peach",
        "price": 36,
        "volume_ml": 350,
        "description": "Słodki koktajl przygotowany z rumu, puree brzoskwiniowego, soku ananasowego i likieru brzoskwiniowego."
      },
      {
        "id": 5,
        "name": "Sirius A&B",
        "price": 37,
        "volume_ml": 700,
        "description": "Dwa koktajle w jednej pozycji."
      },
      {
        "id": 6,
        "name": "Eclipse",
        "price": 69,
        "volume_ml": 380,
        "description": "Kwaśny koktajl przygotowany z tequili, soku pomarańczowego, grenadiny i mięty."
      }
    ],
    "klasyczne_koktajle_swiata": [
      {
        "id": 1,
        "name": "Aperol",
        "price": 38,
        "volume_ml": 300,
        "description": "Słodko‑gorzki klasyczny napój przygotowany z Aperolu, wody gazowanej i prosecco."
      },
      {
        "id": 2,
        "name": "Boulevardier",
        "price": 40,
        "volume_ml": 120,
        "description": "Mocny gorzki koktajl przygotowany z bourbona, Martini Rosso i Campari."
      },
      {
        "id": 3,
        "name": "Cuba Libre",
        "price": 33,
        "volume_ml": 350,
        "description": "Koktajl słodko‑kwaśny przygotowany z rumu, mięty, soku z limonki i coli."
      },
      {
        "id": 4,
        "name": "Daiquiri",
        "price": 34,
        "volume_ml": 110,
        "description": "Kwaśny koktajl z rumem, sokiem z limonki i triple sec."
      },
      {
        "id": 5,
        "name": "God Father",
        "price": 34,
        "volume_ml": 90,
        "description": "Słodki, mocny koktajl zrobiony z bourbona i likieru migdałowego."
      },
      {
        "id": 6,
        "name": "Old Fashioned",
        "price": 36,
        "volume_ml": 75,
        "description": "Słodki, mocny koktajl przygotowany z bourbona, cukru trzcinowego i Angostury."
      },
      {
        "id": 7,
        "name": "Long Island",
        "price": 45,
        "volume_ml": 350,
        "description": "Słodko‑kwaśny koktajl z ginu, wódki, rumu, tequili, triple sec, soku z cytryny i coli."
      },
      {
        "id": 8,
        "name": "Manhattan",
        "price": 40,
        "volume_ml": 90,
        "description": "Gorzki koktajl zrobiony z bourbona, Martini Rosso i Angostury."
      },
      {
        "id": 9,
        "name": "Margarita",
        "price": 36,
        "volume_ml": 120,
        "description": "Kwaśny koktajl z tequilą, likierem triple sec i sokiem z limonki."
      },
      {
        "id": 10,
        "name": "Mojito",
        "price": 38,
        "volume_ml": 350,
        "description": "Kwaśny koktajl z rumem, sokiem z limonki, miętą i Sprite."
      },
      {
        "id": 11,
        "name": "Negroni",
        "price": 37,
        "volume_ml": 90,
        "description": "Gorzki koktajl z ginem, Campari i Martini Rosso."
      },
      {
        "id": 12,
        "name": "Tom Collins",
        "price": 34,
        "volume_ml": 350,
        "description": "Kwaśny koktajl z ginem, cukrem trzcinowym, sokiem z cytryny i wodą gazowaną."
      }
    ],
    "mocktails": [
      {
        "id": 1,
        "name": "Bumblebee",
        "price": 24,
        "volume_ml": 300,
        "description": "Słodko‑gorzki mocktail przygotowany z espresso, soku pomarańczowego i syropu waniliowego."
      },
      {
        "id": 2,
        "name": "Eleanora",
        "price": 24,
        "volume_ml": 350,
        "description": "Słodki tropikalny koktajl bezalkoholowy z soku ananasowego i jabłkowego, puree z marakui oraz syropu melonowego."
      },
      {
        "id": 3,
        "name": "Citrus Blossom",
        "price": 24,
        "volume_ml": 300,
        "description": "Kwaśny koktajl bezalkoholowy z sokiem z pomarańczy, cytryny i limonki, syropem waniliowym i kwiatem bzu."
      },
      {
        "id": 4,
        "name": "Orion",
        "price": 24,
        "volume_ml": 320,
        "description": "Koktajl słodko‑kwaśny z puree z marakui, Sprite i syropu wiśniowego."
      },
      {
        "id": 5,
        "name": "Stargaze",
        "price": 24,
        "volume_ml": 200,
        "description": "Kwaśny drink bezalkoholowy z musem z borówek, sokiem z ananasa i limonki, wanilią i syropem melonowym."
      }
    ],
    "shisha": [
      {
        "id": 1,
        "name": "Shisha Premium",
        "price": 100,
        "description": "Wybierz swoją moc nikotyny 1–7 i ciesz się różnymi smakami."
      },
      {
        "id": 2,
        "name": "Shisha Cigarro",
        "price": 120,
        "description": "Wysokiej jakości liść cygara (bez aromatu). Dobry, czysty i mieszany."
      },
      {
        "id": 3,
        "name": "Shisha Parfume",
        "price": 150,
        "description": "Nowa fala w przemyśle fajek wodnych. Bogata, aromatyczna, inna."
      }
    ],
    "alkohol": {
      "whisky": [
        {
          "name": "Bulleit",
          "price": 29
        },
        {
          "name": "Glenmorangie T.C.",
          "price": 29
        },
        {
          "name": "Jack Daniel’s",
          "price": 26
        },
        {
          "name": "Laphroaig D.O.",
          "price": 43
        },
        {
          "name": "Maker’s Mark",
          "price": 29
        },
        {
          "name": "Nikka Barrel",
          "price": 60
        },
        {
          "name": "Sexton",
          "price": 31
        },
        {
          "name": "Talisker 10 YO",
          "price": 49
        },
        {
          "name": "Tamnavulin D.C.",
          "price": 29
        },
        {
          "name": "Tenjaku",
          "price": 37
        }
      ],
      "gin": [
        {
          "name": "Beefeater",
          "price": 23
        },
        {
          "name": "Bombay",
          "price": 23
        },
        {
          "name": "Gordon’s",
          "price": 20
        },
        {
          "name": "Hendriks",
          "price": 37
        },
        {
          "name": "Roku",
          "price": 26
        },
        {
          "name": "Tenjaku",
          "price": 23
        }
      ],
      "rum": [
        {
          "name": "Bacardi",
          "price": 20
        },
        {
          "name": "Bumbu",
          "price": 29
        },
        {
          "name": "Kraken",
          "price": 26
        },
        {
          "name": "Planteray",
          "price": 43
        }
      ],
      "tequila": [
        {
          "name": "Jimador",
          "price": 22
        },
        {
          "name": "Jose Cuervo",
          "price": 20
        },
        {
          "name": "Patron",
          "price": 45
        },
        {
          "name": "Salitos",
          "price": 26
        }
      ],
      "vodka": [
        {
          "name": "Grey Goose",
          "price": 23
        },
        {
          "name": "Ostoya",
          "price": 23
        },
        {
          "name": "Zubrowka",
          "price": 20
        }
      ],
      "beer": [
        {
          "name": "Amber 0.5",
          "price": 18
        },
        {
          "name": "Ksiazenice 0.5",
          "price": 18
        }
      ]
    },
    "soft": [
      {
        "name": "Cola 0.33",
        "price": 12
      },
      {
        "name": "Sprite 0.33",
        "price": 12
      },
      {
        "name": "Fanta 0.33",
        "price": 12
      },
      {
        "name": "Cisowianka 0.3",
        "price": 10
      }
    ],
    "coffee_tea": [
      {
        "name": "Espresso",
        "price": 10
      },
      {
        "name": "Americano",
        "price": 12
      },
      {
        "name": "Cappuccino",
        "price": 17
      },
      {
        "name": "Latte",
        "price": 19
      },
      {
        "name": "Chinese Tea",
        "price": 35
      }
    ],
    "snacks": [
      {
        "name": "7Days Croissant",
        "price": 6
      },
      {
        "name": "Biscuit Lubusie",
        "price": 4
      },
      {
        "name": "Chips Lay’s",
        "price": 7
      },
      {
        "name": "Mars Chocolate",
        "price": 8
      },
      {
        "name": "Peanuts",
        "price": 16
      },
      {
        "name": "Pistachio",
        "price": 46
      }
    ]
  }
}